README.md
setup.cfg
setup.py
auto1_api/__init__.py
auto1_api/api.py
auto1_api/base.py
auto1_api/exceptions.py
auto1_api/payload.py
auto1_api.egg-info/PKG-INFO
auto1_api.egg-info/SOURCES.txt
auto1_api.egg-info/dependency_links.txt
auto1_api.egg-info/requires.txt
auto1_api.egg-info/top_level.txt