Metadata-Version: 2.1
Name: auto1-api
Version: 0.1.2
Summary: Async library for auto1.by API
Home-page: https://github.com/bl4ckm45k/auto1_api
Author: bl4ckm45k
Author-email: nonpowa@gmail.com
License: Apache License, Version 2.0 see LICENSE file
Platform: UNKNOWN
Classifier: Programming Language :: Python :: 3.10
Classifier: License :: OSI Approved :: MIT License
Classifier: Operating System :: OS Independent
Requires-Python: >=3.7
